pypulate/__init__.py
pypulate/py.typed
pypulate/allocation/__init__.py
pypulate/allocation/optimization.py
pypulate/asset/__init__.py
pypulate/asset/apt.py
pypulate/asset/binomial_tree.py
pypulate/asset/black_scholes.py
pypulate/asset/bond_pricing.py
pypulate/asset/capm.py
pypulate/asset/fama_french.py
pypulate/asset/mean_inversion.py
pypulate/asset/monte_carlo.py
pypulate/asset/risk_neutral.py
pypulate/asset/term_structure.py
pypulate/asset/yield_curve.py
pypulate/credit/__init__.py
pypulate/credit/altman_z_score.py
pypulate/credit/create_scorecard.py
pypulate/credit/debt_service_coverage_ratio.py
pypulate/credit/expected_credit_loss.py
pypulate/credit/exposure_at_default.py
pypulate/credit/financial_ratios.py
pypulate/credit/loan_pricing.py
pypulate/credit/logistic_regression_score.py
pypulate/credit/loss_given_default.py
pypulate/credit/merton_model.py
pypulate/credit/scoring_model_validation.py
pypulate/credit/transition_matrix.py
pypulate/credit/weight_of_evidence.py
pypulate/dtypes/__init__.py
pypulate/dtypes/allocation.py
pypulate/dtypes/credit_scoring.py
pypulate/dtypes/kpi.py
pypulate/dtypes/parray.py
pypulate/dtypes/portfolio.py
pypulate/dtypes/service_pricing.py
pypulate/filters/__init__.py
pypulate/filters/adaptive_filters.py
pypulate/filters/kalman.py
pypulate/filters/particle_filters.py
pypulate/filters/signal_filters.py
pypulate/kpi/__init__.py
pypulate/kpi/business_kpi.py
pypulate/moving_averages/__init__.py
pypulate/moving_averages/movingaverages.py
pypulate/portfolio/__init__.py
pypulate/portfolio/return_measurement.py
pypulate/portfolio/risk_adjusted.py
pypulate/portfolio/risk_measurement.py
pypulate/preprocessing/__init__.py
pypulate/preprocessing/preprocessing.py
pypulate/preprocessing/statistics.py
pypulate/pricing/__init__.py
pypulate/pricing/bundle_pricing.py
pypulate/pricing/dynamic_pricing.py
pypulate/pricing/freemium_pricing.py
pypulate/pricing/loyalty_based_pricing.py
pypulate/pricing/peak_pricing.py
pypulate-0.3.0.dist-info/METADATA
pypulate-0.3.0.dist-info/WHEEL
pypulate-0.3.0.dist-info/licenses/LICENSE
pypulate-0.3.0.dist-info/RECORD
